{
  "customType": "BABYLON.NodeGeometry",
  "outputNodeId": 8,
  "blocks": [
    {
      "customType": "BABYLON.GridBlock",
      "id": 1,
      "name": "plane",
      "inputs": [
        {
          "name": "width",
          "displayName": "width"
        },
        {
          "name": "height",
          "displayName": "height"
        },
        {
          "name": "subdivisions",
          "displayName": "subdivisions"
        },
        {
          "name": "subdivisionsX",
          "displayName": "subdivisionsX"
        },
        {
          "name": "subdivisionsY",
          "displayName": "subdivisionsY"
        }
      ],
      "outputs": [
        {
          "name": "geometry",
          "displayName": "geometry"
        }
      ],
      "evaluateContext": false
    },
    {
      "customType": "BABYLON.GeometryInputBlock",
      "id": 2,
      "name": "positions",
      "inputs": [],
      "outputs": [
        {
          "name": "output",
          "displayName": "output"
        }
      ],
      "type": 8,
      "contextualValue": 1,
      "min": 0,
      "max": 0,
      "groupInInspector": "",
      "displayInInspector": true
    },
    {
      "customType": "BABYLON.NoiseBlock",
      "id": 3,
      "name": "noise",
      "inputs": [
        {
          "name": "offset",
          "displayName": "offset"
        },
        {
          "name": "scale",
          "displayName": "scale"
        },
        {
          "name": "octaves",
          "displayName": "octaves"
        },
        {
          "name": "roughness",
          "displayName": "roughness"
        }
      ],
      "outputs": [
        {
          "name": "output",
          "displayName": "output"
        }
      ]
    },
    {
      "customType": "BABYLON.GeometryInputBlock",
      "id": 4,
      "name": "heightScale",
      "inputs": [],
      "outputs": [
        {
          "name": "output",
          "displayName": "output"
        }
      ],
      "type": 2,
      "contextualValue": 0,
      "min": 0,
      "max": 0,
      "groupInInspector": "",
      "displayInInspector": true,
      "value": 2,
      "valueType": "number"
    },
    {
      "customType": "BABYLON.MathBlock",
      "id": 5,
      "name": "heightMul",
      "inputs": [
        {
          "name": "left",
          "displayName": "left",
          "inputName": "left",
          "targetBlockId": 3,
          "targetConnectionName": "output"
        },
        {
          "name": "right",
          "displayName": "right",
          "inputName": "right",
          "targetBlockId": 4,
          "targetConnectionName": "output"
        }
      ],
      "outputs": [
        {
          "name": "output",
          "displayName": "output"
        }
      ],
      "operation": 2
    },
    {
      "customType": "BABYLON.SetPositionsBlock",
      "id": 6,
      "name": "setPositions",
      "inputs": [
        {
          "name": "geometry",
          "displayName": "geometry",
          "inputName": "geometry",
          "targetBlockId": 1,
          "targetConnectionName": "geometry"
        },
        {
          "name": "positions",
          "displayName": "positions",
          "inputName": "positions",
          "targetBlockId": 5,
          "targetConnectionName": "output"
        }
      ],
      "outputs": [
        {
          "name": "output",
          "displayName": "output"
        }
      ],
      "evaluateContext": true
    },
    {
      "customType": "BABYLON.ComputeNormalsBlock",
      "id": 7,
      "name": "normals",
      "inputs": [
        {
          "name": "geometry",
          "displayName": "geometry",
          "inputName": "geometry",
          "targetBlockId": 6,
          "targetConnectionName": "output"
        }
      ],
      "outputs": [
        {
          "name": "output",
          "displayName": "output"
        }
      ]
    },
    {
      "customType": "BABYLON.GeometryOutputBlock",
      "id": 8,
      "name": "output",
      "inputs": [
        {
          "name": "geometry",
          "displayName": "geometry",
          "inputName": "geometry",
          "targetBlockId": 7,
          "targetConnectionName": "output"
        }
      ],
      "outputs": []
    }
  ],
  "comment": "Deform a plane with Perlin noise to create terrain.",
  "editorData": {
    "locations": [
      {
        "blockId": 1,
        "x": 680,
        "y": 0
      },
      {
        "blockId": 2,
        "x": 0,
        "y": 0
      },
      {
        "blockId": 3,
        "x": 340,
        "y": 0
      },
      {
        "blockId": 4,
        "x": 340,
        "y": 180
      },
      {
        "blockId": 5,
        "x": 680,
        "y": 180
      },
      {
        "blockId": 6,
        "x": 1020,
        "y": 0
      },
      {
        "blockId": 7,
        "x": 1360,
        "y": 0
      },
      {
        "blockId": 8,
        "x": 1700,
        "y": 0
      }
    ]
  }
}